cacao_json_viewer/__init__.py
cacao_json_viewer/cli.py
cacao_json_viewer/viewer.py
cacao_json_viewer-0.1.1.dist-info/licenses/LICENSE
cacao_json_viewer-0.1.1.dist-info/METADATA
cacao_json_viewer-0.1.1.dist-info/WHEEL
cacao_json_viewer-0.1.1.dist-info/entry_points.txt
cacao_json_viewer-0.1.1.dist-info/top_level.txt
cacao_json_viewer-0.1.1.dist-info/RECORD
