Metadata-Version: 2.4
Name: cacao-json-viewer
Version: 0.1.1
Summary: A simple JSON/tree viewer desktop app built on Cacao
Author-email: Juan Denis <juan@vene.co>
License-Expression: MIT
Requires-Python: >=3.8
License-File: LICENSE
Requires-Dist: cacao>=1.0.40
Dynamic: license-file
